{
  "version": 3,
  "middleware": {
    "/": {
      "files": [
        "server/edge-runtime-webpack.js",
        "server/middleware.js"
      ],
      "name": "middleware",
      "page": "/",
      "matchers": [
        {
          "regexp": "^(?:\\/(_next\\/data\\/[^/]{1,}))?(?:\\/((?!api|trpc|_next\\/|_vercel|favicon\\.ico|images\\/|.*\\..*).*))(.json)?[\\/#\\?]?$",
          "originalSource": "/((?!api|trpc|_next/|_vercel|favicon\\.ico|images/|.*\\..*).*)"
        }
      ],
      "wasm": [],
      "assets": [],
      "env": {
        "__NEXT_BUILD_ID": "EaS5SqZ7g1OiIReD03kEy",
        "NEXT_SERVER_ACTIONS_ENCRYPTION_KEY": "tpCseuP3UWKLxYI64AwT0mrFfyJor1Ysj0KOfly0nMM=",
        "__NEXT_PREVIEW_MODE_ID": "425557a60ff6e6a9dd488c3deda15bc1",
        "__NEXT_PREVIEW_MODE_ENCRYPTION_KEY": "7fad3537d488222c35f0ea0c6b33463d45aa9ff74eeda9d77e3f1bc071f5b91a",
        "__NEXT_PREVIEW_MODE_SIGNING_KEY": "3ec295455b55b30355157799ab4d224ecf6c3f9b15e7dfd3b9867905d4dabff6"
      }
    }
  },
  "functions": {},
  "sortedMiddleware": [
    "/"
  ]
}